timecache/__init__.py
timecache/cachentry.py
timecache/consts.py
timecache/timecache.py
timecache/backends/__init__.py
timecache/backends/basebackend.py
timecache/backends/filebackend.py
timecache/backends/jsonbackend.py
timecache/backends/memorybackend.py
timecache/backends/picklebackend.py
timecache-0.0.3.dist-info/METADATA
timecache-0.0.3.dist-info/RECORD
timecache-0.0.3.dist-info/WHEEL
timecache-0.0.3.dist-info/top_level.txt
