Metadata-Version: 2.1
Name: timecache
Version: 0.0.3
Summary: Time Cache
Home-page: https://github.com
Author: Ansgar Kellner
Author-email: keans@gmx.net
License: MIT
Keywords: python packaging
Platform: UNKNOWN
Classifier: Development Status :: 3 - Alpha
Classifier: Intended Audience :: Developers
Classifier: Topic :: Software Development :: Build Tools
Classifier: License :: OSI Approved :: MIT License
Classifier: Programming Language :: Python :: 3
Classifier: Programming Language :: Python :: 3.5
Classifier: Programming Language :: Python :: 3.6
Classifier: Programming Language :: Python :: 3.7
